MANIFEST.in
README.rst
setup.py
c2c/__init__.py
c2c/cssmin_.py
c2c.cssmin.egg-info/PKG-INFO
c2c.cssmin.egg-info/SOURCES.txt
c2c.cssmin.egg-info/dependency_links.txt
c2c.cssmin.egg-info/entry_points.txt
c2c.cssmin.egg-info/namespace_packages.txt
c2c.cssmin.egg-info/requires.txt
c2c.cssmin.egg-info/top_level.txt