Metadata-Version: 1.1
Name: c2c.cssmin
Version: 0.7dev6
Summary: A command to merge and compress css files
Home-page: https://github.com/camptocamp/c2c.cssmin
Author: Camptocamp
Author-email: info@camptocamp.com
License: MIT License
Keywords: css,cssmin
Platform: UNKNOWN
Classifier: Intended Audience :: Developers
Classifier: Topic :: Software Development :: Build Tools
Classifier: Topic :: Software Development :: Libraries :: Python Modules
Classifier: License :: OSI Approved :: MIT License
